Metadata-Version: 2.1
Name: soda-core-bigquery
Version: 3.5.6
License-File: LICENSE
Requires-Dist: soda-core==3.5.6
Requires-Dist: google-cloud-bigquery<4.0,>=2.25.0
